ucis/__init__.py
ucis/__main__.py
ucis/cov_scope.py
ucis/cover_data.py
ucis/cover_flags_t.py
ucis/cover_index.py
ucis/cover_instance.py
ucis/cover_item.py
ucis/cover_type.py
ucis/cover_type_t.py
ucis/covergroup.py
ucis/coverpoint.py
ucis/cross.py
ucis/cvg_bin_scope.py
ucis/cvg_scope.py
ucis/db.py
ucis/db_format_rgy.py
ucis/du_scope.py
ucis/file_handle.py
ucis/filter_rgy.py
ucis/flags_t.py
ucis/func_cov_scope.py
ucis/handle_property.py
ucis/history_node.py
ucis/history_node_kind.py
ucis/ignore_bin_scope.py
ucis/illegal_bin_scope.py
ucis/instance_coverage.py
ucis/instance_scope.py
ucis/int_property.py
ucis/name_value.py
ucis/obj.py
ucis/real_property.py
ucis/scope.py
ucis/scope_type_t.py
ucis/source_file.py
ucis/source_info.py
ucis/source_t.py
ucis/statement_id.py
ucis/str_property.py
ucis/test_data.py
ucis/test_status_t.py
ucis/toggle_dir_t.py
ucis/toggle_metric_t.py
ucis/toggle_type_t.py
ucis/ucis.py
ucis/unimpl_error.py
ucis/cmd/__init__.py
ucis/cmd/cmd_convert.py
ucis/cmd/cmd_list_db_formats.py
ucis/cmd/cmd_list_report_formats.py
ucis/cmd/cmd_merge.py
ucis/cmd/cmd_report.py
ucis/lib/LibFactory.py
ucis/lib/__init__.py
ucis/lib/db_format_if_lib.py
ucis/lib/lib_cover_data.py
ucis/lib/lib_cover_index.py
ucis/lib/lib_cover_type.py
ucis/lib/lib_covergroup.py
ucis/lib/lib_coverpoint.py
ucis/lib/lib_cross.py
ucis/lib/lib_cvg_scope.py
ucis/lib/lib_file_handle.py
ucis/lib/lib_history_node.py
ucis/lib/lib_history_node_iterator.py
ucis/lib/lib_obj.py
ucis/lib/lib_scope.py
ucis/lib/lib_scope_iterator.py
ucis/lib/lib_source_info.py
ucis/lib/lib_test_data.py
ucis/lib/lib_ucis.py
ucis/lib/libucis.py
ucis/mem/__init__.py
ucis/mem/db_format_if_mem.py
ucis/mem/mem_cover_index.py
ucis/mem/mem_cover_index_iterator.py
ucis/mem/mem_cover_item.py
ucis/mem/mem_cover_type.py
ucis/mem/mem_covergroup.py
ucis/mem/mem_coverpoint.py
ucis/mem/mem_cross.py
ucis/mem/mem_cvg_scope.py
ucis/mem/mem_du_scope.py
ucis/mem/mem_factory.py
ucis/mem/mem_file_handle.py
ucis/mem/mem_history_node.py
pyucis-0.1.4.11087239919.dist-info/LICENSE
pyucis-0.1.4.11087239919.dist-info/METADATA
pyucis-0.1.4.11087239919.dist-info/WHEEL
pyucis-0.1.4.11087239919.dist-info/entry_points.txt
pyucis-0.1.4.11087239919.dist-info/top_level.txt
pyucis-0.1.4.11087239919.dist-info/RECORD
