Metadata-Version: 2.1
Name: pyucis
Version: 0.1.4.11087239919
Summary: PyUCIS provides a Python API for manipulating UCIS coverage data.
Home-page: https://github.com/fvutils/pyucis
Author: Matthew Ballance
Author-email: matt.ballance@gmail.com
License: Apache 2.0
Keywords: SystemVerilog,Verilog,RTL,Coverage
License-File: LICENSE
Requires-Dist: lxml
Requires-Dist: python-jsonschema-objects
Requires-Dist: jsonschema
Requires-Dist: pyyaml
